candystore/__init__.py
candystore/base_data.py
candystore/betting_odds.py
candystore/fixtures.py
candystore/match_results.py
candystore/players.py
docs/__init__.py
docs/source/__init__.py
docs/source/conf.py
tests/__init__.py
tests/test_candystore_data.py
tests/integration/__init__.py
tests/integration/test_fitzroy_compatibility.py
candystore-0.3.4.dist-info/LICENSE
candystore-0.3.4.dist-info/METADATA
candystore-0.3.4.dist-info/WHEEL
candystore-0.3.4.dist-info/top_level.txt
candystore-0.3.4.dist-info/RECORD
