Metadata-Version: 2.1
Name: candystore
Version: 0.3.4
Summary: Factories for randomised AFL data sets for testing purposes
Home-page: https://github.com/tipresias/candystore
Author: Craig Franklin
Author-email: craigjfranklin@gmail.com
License: UNKNOWN
Platform: UNKNOWN
Classifier: Programming Language :: Python :: 3
Classifier: License :: OSI Approved :: MIT License
Classifier: Operating System :: OS Independent
Requires-Python: >=3.6
Requires-Dist: numpy
Requires-Dist: pandas
Requires-Dist: faker
Requires-Dist: mypy
